MANIFEST.in
README.rst
setup.cfg
setup.py
versioneer.py
src/leap/__init__.py
src/leap.bonafide.egg-info/PKG-INFO
src/leap.bonafide.egg-info/SOURCES.txt
src/leap.bonafide.egg-info/dependency_links.txt
src/leap.bonafide.egg-info/entry_points.txt
src/leap.bonafide.egg-info/namespace_packages.txt
src/leap.bonafide.egg-info/not-zip-safe
src/leap.bonafide.egg-info/pbr.json
src/leap.bonafide.egg-info/requires.txt
src/leap.bonafide.egg-info/top_level.txt
src/leap/bonafide/__init__.py
src/leap/bonafide/_http.py
src/leap/bonafide/_protocol.py
src/leap/bonafide/_srp.py
src/leap/bonafide/_version.py
src/leap/bonafide/bootstrap.py
src/leap/bonafide/config.py
src/leap/bonafide/cred_srp.py
src/leap/bonafide/provider.py
src/leap/bonafide/service.py
src/leap/bonafide/session.py
src/leap/bonafide/ssh_service.py
src/leap/bonafide/services/__init__.py
src/leap/bonafide/services/eip.py
src/leap/bonafide/services/mail.py
src/leap/bonafide/services/soledad.py
src/leap/bonafide/tests/__init__.py