Metadata-Version: 1.1
Name: leap.bonafide
Version: 0.0.2
Summary: Common files used by the LEAP project.
Home-page: https://leap.se/
Author: Kali Kaneko
Author-email: kali@leap.se
License: GPLv3+
Platform: UNKNOWN
Classifier: Development Status :: 3 - Alpha
Classifier: Intended Audience :: Developers
Classifier: License :: OSI Approved :: GNU General Public License v3 or later (GPLv3+)
Classifier: Operating System :: OS Independent
Classifier: Programming Language :: Python
Classifier: Programming Language :: Python :: 2.7
Classifier: Topic :: Communications
Classifier: Topic :: Security
Classifier: Topic :: Utilities
